mypy2junit.py
mypy2junit-1.9.0.dist-info/METADATA
mypy2junit-1.9.0.dist-info/WHEEL
mypy2junit-1.9.0.dist-info/entry_points.txt
mypy2junit-1.9.0.dist-info/top_level.txt
mypy2junit-1.9.0.dist-info/RECORD
