Metadata-Version: 2.1
Name: mypy2junit
Version: 1.9.0
Summary: Script for converting output from MyPy to Junit XML format
Home-page: https://github.com/Dundee/mypy2junit
Author: Daniel Milde
Author-email: daniel@milde.cz
License: BSD-3-Clause
Classifier: Programming Language :: Python
Classifier: Programming Language :: Python :: 3
Requires-Python: >=3.5
Provides-Extra: dev
Requires-Dist: pytest ; extra == 'dev'
